{"368423564229083137": {"wallet": 21.0, "xp": 89, "speak_cooldown": 1651330252.6934261, "marriage": {}, "inventory": {}, "daily": {"day": 19112, "streak": 1}}, "465212503060905994": {"wallet": 31.0, "xp": 6, "speak_cooldown": 1651318340.4913428, "marriage": {}, "inventory": {}, "daily": {"day": 0, "streak": 0}}, "302463870046568449": {"wallet": 33.0, "xp": 5, "speak_cooldown": 1651283708.59761, "marriage": {}, "inventory": {}}, "411536312961597440": {"wallet": 193.0, "xp": 41, "speak_cooldown": 1651330192.865128, "marriage": {}, "inventory": {}, "daily": {"day": 19112, "streak": 1}}, "689565874612469784": {"wallet": 259.0, "xp": 53, "speak_cooldown": 1651330147.7414749, "marriage": {}, "inventory": {}, "daily": {"day": 19112, "streak": 1}}, "705399466710007908": {"wallet": 73.0, "xp": 21, "speak_cooldown": 1651307757.8676033, "marriage": {}, "inventory": {}}, "417855406224965642": {"wallet": 23.0, "xp": 3, "speak_cooldown": 1651250318.8699331, "marriage": {}, "inventory": {}}, "765222621779853312": {"wallet": 11.0, "xp": 1, "speak_cooldown": 1651088454.6433423, "marriage": {}}, "877322068499238912": {"wallet": 239.5, "xp": 71, "speak_cooldown": 1651319834.3663855, "marriage": {}, "inventory": {}, "daily": {"day": 0, "streak": 0}}, "767845502129537035": {"wallet": 10.0, "xp": 0, "speak_cooldown": 1651088632.3247247, "marriage": {}}, "102862012689690624": {"wallet": 1.0, "xp": 1, "speak_cooldown": 1651089558.6506107, "marriage": {}}, "248859702547578881": {"wallet": 40.0, "xp": 9, "speak_cooldown": 1651267889.4487655, "marriage": {}, "inventory": {}}, "398181370725400577": {"wallet": 278.5, "xp": 64, "speak_cooldown": 1651329382.5732162, "marriage": {}, "inventory": {}, "daily": {"day": 19112, "streak": 1}}, "589502283428003901": {"wallet": 52.0, "xp": 12, "speak_cooldown": 1651304947.051623, "marriage": {}, "inventory": {}}, "325325337615532054": {"wallet": 98.0, "xp": 28, "speak_cooldown": 1651313743.9481952, "marriage": {}, "inventory": {}, "daily": {"day": 0, "streak": 0}}, "480379728478470144": {"wallet": 57.0, "xp": 13, "speak_cooldown": 1651315041.2241366, "marriage": {}, "inventory": {}, "daily": {"day": 0, "streak": 0}}, "269537437242359811": {"wallet": 33.0, "xp": 5, "speak_cooldown": 1651330138.4241247, "marriage": {}, "inventory": {}, "daily": {"day": 0, "streak": 0}}, "499892410667630592": {"wallet": 84.0, "xp": 21, "speak_cooldown": 1651226565.2843168, "marriage": {}, "inventory": {}}, "639851373076283413": {"wallet": 12.0, "xp": 1, "speak_cooldown": 1651233092.7576025, "marriage": {}, "inventory": {}}, "328464792702550016": {"wallet": 69.0, "xp": 15, "speak_cooldown": 1651270593.2303734, "marriage": {}, "inventory": {}}, "192326730948542464": {"wallet": 51.0, "xp": 11, "speak_cooldown": 1651330519.546933, "marriage": {}, "inventory": {}, "daily": {"day": 0, "streak": 0}}, "480410500434231306": {"wallet": 54.0, "xp": 12, "speak_cooldown": 1651241906.886725, "marriage": {}, "inventory": {}}, "687678861898416326": {"wallet": 39.0, "xp": 8, "speak_cooldown": 1651330602.7576103, "marriage": {}, "inventory": {}, "daily": {"day": 0, "streak": 0}}, "457246804606451715": {"wallet": 29.0, "xp": 6, "speak_cooldown": 1651253152.3217378, "marriage": {}, "inventory": {}}, "726433344862027797": {"wallet": 58.0, "xp": 17, "speak_cooldown": 1651312869.172491, "marriage": {}, "inventory": {}, "daily": {"day": 0, "streak": 0}}, "645969806104723456": {"wallet": 33.0, "xp": 7, "speak_cooldown": 1651264448.5554733, "marriage": {}, "inventory": {}}, "698653256582430750": {"wallet": 10.0, "xp": 0, "speak_cooldown": 1651143220.2812953, "marriage": {}}, "274191444070105090": {"wallet": 19.0, "xp": 2, "speak_cooldown": 1651152996.9516594, "marriage": {}}, "319426876533768193": {"wallet": 19.0, "xp": 2, "speak_cooldown": 1651153979.0492175, "marriage": {}}, "879252537268666398": {"wallet": 72.0, "xp": 3, "speak_cooldown": 1651327861.5423172, "marriage": {}, "inventory": {}, "daily": {"day": 19112, "streak": 1}}, "551088379983298560": {"wallet": 26.0, "xp": 5, "speak_cooldown": 1651159764.838804, "marriage": {}}, "343814584257478657": {"wallet": 31.0, "xp": 7, "speak_cooldown": 1651212847.5375257, "marriage": {}, "inventory": {}}, "338627190956490753": {"wallet": 93.5, "xp": 8, "speak_cooldown": 1651329967.8712916, "marriage": {}, "inventory": {}, "daily": {"day": 19112, "streak": 1}}, "349146665917087745": {"wallet": 12.0, "xp": 1, "speak_cooldown": 1651179084.6266506, "marriage": {}, "inventory": {}}, "768076078346141717": {"wallet": 10.0, "xp": 0, "speak_cooldown": 1651265891.377654, "marriage": {}, "inventory": {}}}